{
  "project_info": {
    "project_number": "600065728239",
    "project_id": "chat-app-543",
    "storage_bucket": "chat-app-543.appspot.com"
  },
  "client": [
    {
      "client_info": {
        "mobilesdk_app_id": "1:600065728239:android:b63d684d2025af5afb451a",
        "android_client_info": {
          "package_name": "com.example.chat_app"
        }
      },
      "oauth_client": [],
      "api_key": [
        {
          "current_key": "AIzaSyCRgXOHVMHRhTMC3wSthzezkyJSfvakaiE"
        }
      ],
      "services": {
        "appinvite_service": {
          "other_platform_oauth_client": []
        }
      }
    }
  ],
  "configuration_version": "1"
}